tieto_pika_pkg/__init__.py
tieto_pika_pkg/agent.py
tieto_pika_pkg/config.py
tieto_pika_pkg/exceptions.py
tieto_pika_pkg/g0_receive.py
tieto_pika_pkg/g0_send.py
tieto_pika_pkg/test_ai_project/__init__.py
tieto_pika_pkg/test_ai_project/test_g0_receive_result.py
tieto_pika_pkg/test_ai_project/test_g0_send.py
tieto_pika_pkg/test_ai_project/test_task_message.py
pika_pika_smart-0.1.1.dist-info/LICENSE
pika_pika_smart-0.1.1.dist-info/METADATA
pika_pika_smart-0.1.1.dist-info/WHEEL
pika_pika_smart-0.1.1.dist-info/top_level.txt
pika_pika_smart-0.1.1.dist-info/RECORD
